fw_gear_dicom_qc/__init__.py
fw_gear_dicom_qc/empty-json-schema.json
fw_gear_dicom_qc/main.py
fw_gear_dicom_qc/parser.py
fw_gear_dicom_qc/rules.py
fw_gear_dicom_qc/utils.py
fw_gear_dicom_qc/validation.py
fw_gear_dicom_qc-0.5.1.dist-info/LICENSE
fw_gear_dicom_qc-0.5.1.dist-info/METADATA
fw_gear_dicom_qc-0.5.1.dist-info/WHEEL
fw_gear_dicom_qc-0.5.1.dist-info/RECORD
